inferdecode/__init__.py
inferdecode/base_decoder.py
inferdecode/cli.py
inferdecode/decode_tui.py
inferdecode/hf_decoder.py
inferdecode-0.1.3.dist-info/licenses/LICENSE
inferdecode-0.1.3.dist-info/METADATA
inferdecode-0.1.3.dist-info/WHEEL
inferdecode-0.1.3.dist-info/entry_points.txt
inferdecode-0.1.3.dist-info/top_level.txt
inferdecode-0.1.3.dist-info/RECORD
